a2a/__init__.py
a2a/routes.py
attach/__init__.py
attach/__main__.py
attach/gateway.py
attach_pydid/__init__.py
auth/__init__.py
auth/did.py
auth/oidc.py
logs/__init__.py
mem/__init__.py
mem/sakana.py
mem/weaviate.py
middleware/__init__.py
middleware/auth.py
middleware/quota.py
middleware/session.py
proxy/__init__.py
proxy/engine.py
usage/__init__.py
usage/backends.py
usage/factory.py
usage/metrics.py
utils/env.py
attach_dev-0.3.7.dist-info/METADATA
attach_dev-0.3.7.dist-info/WHEEL
attach_dev-0.3.7.dist-info/entry_points.txt
attach_dev-0.3.7.dist-info/licenses/LICENSE
attach_dev-0.3.7.dist-info/RECORD
