Metadata-Version: 2.4
Name: attach-dev
Version: 0.3.7
Summary: Identity & Memory side-car for every LLM engine and multi-agent framework
Project-URL: Homepage, https://github.com/attach-dev/attach-gateway
Project-URL: Repository, https://github.com/attach-dev/attach-gateway
Author-email: Hammad Tariq <hammad@attach.dev>
License: MIT License
License-File: LICENSE
Keywords: agents,ai,auth,fastapi,llm,memory,sso
Classifier: Development Status :: 4 - Beta
Classifier: Intended Audience :: Developers
Classifier: License :: OSI Approved :: MIT License
Classifier: Programming Language :: Python :: 3
Classifier: Programming Language :: Python :: 3.9
Classifier: Programming Language :: Python :: 3.10
Classifier: Programming Language :: Python :: 3.11
Classifier: Programming Language :: Python :: 3.12
Requires-Python: >=3.9
Requires-Dist: click>=8.0.0
Requires-Dist: fastapi>=0.109.0
Requires-Dist: httpx>=0.27.0
Requires-Dist: python-dotenv>=1.0.0
Requires-Dist: python-jose[cryptography]>=3.3.0
Requires-Dist: uvicorn>=0.27.0
Requires-Dist: weaviate-client<4.0.0,>=3.26.7
Provides-Extra: dev
Requires-Dist: black>=24.1.0; extra == 'dev'
Requires-Dist: isort>=5.13.0; extra == 'dev'
Requires-Dist: pytest-asyncio>=0.23.0; extra == 'dev'
Requires-Dist: pytest>=8.0.0; extra == 'dev'
Provides-Extra: full
Requires-Dist: prometheus-client>=0.20.0; extra == 'full'
Requires-Dist: tiktoken>=0.5.0; extra == 'full'
Provides-Extra: quota
Requires-Dist: tiktoken>=0.5.0; extra == 'quota'
Provides-Extra: usage
Requires-Dist: prometheus-client>=0.20.0; extra == 'usage'
